{
  "last_full_rebuild_iso": "2026-05-14T10:17:24.330Z",
  "tickers": {
    "CSCO": {
      "high_52wk_t1": 101.87000274658203,
      "high_52wk_t2": 99.29000091552734,
      "high_52wk_t3": 98.72000122070312,
      "t1_close": 101.87000274658203,
      "t2_close": 99.29000091552734,
      "yesterday_was_52w_high": true,
      "t2_was_52w_high": true,
      "cached_for_trading_date": "2026-05-13"
    },
    "BTC-USD": {
      "high_52wk_t1": 124752.53125,
      "high_52wk_t2": 124752.53125,
      "high_52wk_t3": 124752.53125,
      "t1_close": 79277.1171875,
      "t2_close": 80477.4921875,
      "yesterday_was_52w_high": false,
      "t2_was_52w_high": false,
      "cached_for_trading_date": "2026-05-13"
    },
    "QUCY": {
      "high_52wk_t1": 2.4700000286102295,
      "high_52wk_t2": 2.5399999618530273,
      "high_52wk_t3": 2.5399999618530273,
      "t1_close": 1.340000033378601,
      "t2_close": 0.3230000138282776,
      "yesterday_was_52w_high": false,
      "t2_was_52w_high": false,
      "cached_for_trading_date": "2026-05-13"
    },
    "MRVL": {
      "high_52wk_t1": 177.9499969482422,
      "high_52wk_t2": 172.14999389648438,
      "high_52wk_t3": 172.14999389648438,
      "t1_close": 177.9499969482422,
      "t2_close": 164.5,
      "yesterday_was_52w_high": true,
      "t2_was_52w_high": false,
      "cached_for_trading_date": "2026-05-13"
    },
    "NOK": {
      "high_52wk_t1": 14.710000038146973,
      "high_52wk_t2": 13.920000076293945,
      "high_52wk_t3": 13.920000076293945,
      "t1_close": 14.710000038146973,
      "t2_close": 13.170000076293945,
      "yesterday_was_52w_high": true,
      "t2_was_52w_high": false,
      "cached_for_trading_date": "2026-05-13"
    },
    "ONDS": {
      "high_52wk_t1": 14.010000228881836,
      "high_52wk_t2": 14.010000228881836,
      "high_52wk_t3": 14.010000228881836,
      "t1_close": 8.859999656677246,
      "t2_close": 9.039999961853027,
      "yesterday_was_52w_high": false,
      "t2_was_52w_high": false,
      "cached_for_trading_date": "2026-05-13"
    },
    "F": {
      "high_52wk_t1": 14.430000305175781,
      "high_52wk_t2": 14.430000305175781,
      "high_52wk_t3": 14.430000305175781,
      "t1_close": 13.569999694824219,
      "t2_close": 11.989999771118164,
      "yesterday_was_52w_high": false,
      "t2_was_52w_high": false,
      "cached_for_trading_date": "2026-05-13"
    },
    "AIIO": {
      "high_52wk_t1": 54.400001525878906,
      "high_52wk_t2": 54.400001525878906,
      "high_52wk_t3": 54.400001525878906,
      "t1_close": 2.609999895095825,
      "t2_close": 1.2799999713897705,
      "yesterday_was_52w_high": false,
      "t2_was_52w_high": false,
      "cached_for_trading_date": "2026-05-13"
    },
    "CBRS-USD": {
      "high_52wk_t1": 299.69287109375,
      "high_52wk_t2": 299.69287109375,
      "high_52wk_t3": 299.69287109375,
      "t1_close": 289.38055419921875,
      "t2_close": 294.92303466796875,
      "yesterday_was_52w_high": false,
      "t2_was_52w_high": false,
      "cached_for_trading_date": "2026-05-13"
    },
    "III.L": {
      "high_52wk_t1": 4459,
      "high_52wk_t2": 4459,
      "high_52wk_t3": 4459,
      "t1_close": 2421,
      "t2_close": 2400,
      "yesterday_was_52w_high": false,
      "t2_was_52w_high": false,
      "cached_for_trading_date": "2026-05-13"
    },
    "NIO": {
      "high_52wk_t1": 7.889999866485596,
      "high_52wk_t2": 7.889999866485596,
      "high_52wk_t3": 7.889999866485596,
      "t1_close": 6.539999961853027,
      "t2_close": 6.079999923706055,
      "yesterday_was_52w_high": false,
      "t2_was_52w_high": false,
      "cached_for_trading_date": "2026-05-13"
    },
    "NVDA": {
      "high_52wk_t1": 225.8300018310547,
      "high_52wk_t2": 220.77999877929688,
      "high_52wk_t3": 219.44000244140625,
      "t1_close": 225.8300018310547,
      "t2_close": 220.77999877929688,
      "yesterday_was_52w_high": true,
      "t2_was_52w_high": true,
      "cached_for_trading_date": "2026-05-13"
    },
    "INVZ": {
      "high_52wk_t1": 2.380000114440918,
      "high_52wk_t2": 2.380000114440918,
      "high_52wk_t3": 2.380000114440918,
      "t1_close": 0.9169999957084656,
      "t2_close": 0.7860000133514404,
      "yesterday_was_52w_high": false,
      "t2_was_52w_high": false,
      "cached_for_trading_date": "2026-05-13"
    },
    "ETH-USD": {
      "high_52wk_t1": 4715.24609375,
      "high_52wk_t2": 4715.24609375,
      "high_52wk_t3": 4715.24609375,
      "t1_close": 2257.576416015625,
      "t2_close": 2274.6435546875,
      "yesterday_was_52w_high": false,
      "t2_was_52w_high": false,
      "cached_for_trading_date": "2026-05-13"
    },
    "EOSE": {
      "high_52wk_t1": 19.190000534057617,
      "high_52wk_t2": 19.190000534057617,
      "high_52wk_t3": 19.190000534057617,
      "t1_close": 8.279999732971191,
      "t2_close": 8.100000381469727,
      "yesterday_was_52w_high": false,
      "t2_was_52w_high": false,
      "cached_for_trading_date": "2026-05-13"
    },
    "HPE": {
      "high_52wk_t1": 32.06999969482422,
      "high_52wk_t2": 31.350000381469727,
      "high_52wk_t3": 31.350000381469727,
      "t1_close": 32.06999969482422,
      "t2_close": 30.209999084472656,
      "yesterday_was_52w_high": true,
      "t2_was_52w_high": false,
      "cached_for_trading_date": "2026-05-13"
    },
    "TDIC": {
      "high_52wk_t1": 36.349998474121094,
      "high_52wk_t2": 36.349998474121094,
      "high_52wk_t3": 36.349998474121094,
      "t1_close": 23.049999237060547,
      "t2_close": 2.359999895095825,
      "yesterday_was_52w_high": false,
      "t2_was_52w_high": false,
      "cached_for_trading_date": "2026-05-13"
    },
    "RR": {
      "high_52wk_t1": 7.059999942779541,
      "high_52wk_t2": 7.059999942779541,
      "high_52wk_t3": 7.059999942779541,
      "t1_close": 2.819999933242798,
      "t2_close": 2.569999933242798,
      "yesterday_was_52w_high": false,
      "t2_was_52w_high": false,
      "cached_for_trading_date": "2026-05-13"
    },
    "XRP-USD": {
      "high_52wk_t1": 3.121467113494873,
      "high_52wk_t2": 3.121467113494873,
      "high_52wk_t3": 3.121467113494873,
      "t1_close": 1.426345944404602,
      "t2_close": 1.436100959777832,
      "yesterday_was_52w_high": false,
      "t2_was_52w_high": false,
      "cached_for_trading_date": "2026-05-13"
    },
    "DOCS": {
      "high_52wk_t1": 75.12000274658203,
      "high_52wk_t2": 75.12000274658203,
      "high_52wk_t3": 75.12000274658203,
      "t1_close": 23.389999389648438,
      "t2_close": 26.450000762939453,
      "yesterday_was_52w_high": false,
      "t2_was_52w_high": false,
      "cached_for_trading_date": "2026-05-13"
    },
    "LGEN.L": {
      "high_52wk_t1": 275.29998779296875,
      "high_52wk_t2": 275.29998779296875,
      "high_52wk_t3": 275.29998779296875,
      "t1_close": 248.5,
      "t2_close": 245.10000610351562,
      "yesterday_was_52w_high": false,
      "t2_was_52w_high": false,
      "cached_for_trading_date": "2026-05-13"
    },
    "FRVO": {
      "high_52wk_t1": 36.540000915527344,
      "high_52wk_t2": null,
      "high_52wk_t3": null,
      "t1_close": 36.540000915527344,
      "yesterday_was_52w_high": true,
      "t2_was_52w_high": false,
      "cached_for_trading_date": "2026-05-13"
    },
    "DXF": {
      "high_52wk_t1": 7.909999847412109,
      "high_52wk_t2": 8,
      "high_52wk_t3": 8,
      "t1_close": 0.7599999904632568,
      "t2_close": 0.5899999737739563,
      "yesterday_was_52w_high": false,
      "t2_was_52w_high": false,
      "cached_for_trading_date": "2026-05-13"
    },
    "FRMI": {
      "high_52wk_t1": 32.529998779296875,
      "high_52wk_t2": 32.529998779296875,
      "high_52wk_t3": 32.529998779296875,
      "t1_close": 6,
      "t2_close": 5.46999979019165,
      "yesterday_was_52w_high": false,
      "t2_was_52w_high": false,
      "cached_for_trading_date": "2026-05-13"
    },
    "KULR": {
      "high_52wk_t1": 12.880000114440918,
      "high_52wk_t2": 12.880000114440918,
      "high_52wk_t3": 12.880000114440918,
      "t1_close": 4.050000190734863,
      "t2_close": 3.190000057220459,
      "yesterday_was_52w_high": false,
      "t2_was_52w_high": false,
      "cached_for_trading_date": "2026-05-13"
    },
    "PLUG": {
      "high_52wk_t1": 4.130000114440918,
      "high_52wk_t2": 4.130000114440918,
      "high_52wk_t3": 4.130000114440918,
      "t1_close": 3.9600000381469727,
      "t2_close": 3.559999942779541,
      "yesterday_was_52w_high": false,
      "t2_was_52w_high": false,
      "cached_for_trading_date": "2026-05-13"
    },
    "INTC": {
      "high_52wk_t1": 129.44000244140625,
      "high_52wk_t2": 129.44000244140625,
      "high_52wk_t3": 129.44000244140625,
      "t1_close": 120.29000091552734,
      "t2_close": 120.61000061035156,
      "yesterday_was_52w_high": false,
      "t2_was_52w_high": false,
      "cached_for_trading_date": "2026-05-13"
    },
    "CTRA": {
      "high_52wk_t1": 36.310001373291016,
      "high_52wk_t2": 36.310001373291016,
      "high_52wk_t3": 36.310001373291016,
      "t1_close": 32.560001373291016,
      "t2_close": 32.560001373291016,
      "yesterday_was_52w_high": false,
      "t2_was_52w_high": false,
      "cached_for_trading_date": "2026-05-07"
    },
    "VNET": {
      "high_52wk_t1": 14.029999732971191,
      "high_52wk_t2": 14.029999732971191,
      "high_52wk_t3": 14.029999732971191,
      "t1_close": 11.279999732971191,
      "t2_close": 9.020000457763672,
      "yesterday_was_52w_high": false,
      "t2_was_52w_high": false,
      "cached_for_trading_date": "2026-05-13"
    },
    "TSLA": {
      "high_52wk_t1": 489.8800048828125,
      "high_52wk_t2": 489.8800048828125,
      "high_52wk_t3": 489.8800048828125,
      "t1_close": 445.2699890136719,
      "t2_close": 433.45001220703125,
      "yesterday_was_52w_high": false,
      "t2_was_52w_high": false,
      "cached_for_trading_date": "2026-05-13"
    },
    "QS": {
      "high_52wk_t1": 18.440000534057617,
      "high_52wk_t2": 18.440000534057617,
      "high_52wk_t3": 18.440000534057617,
      "t1_close": 8.65999984741211,
      "t2_close": 8.420000076293945,
      "yesterday_was_52w_high": false,
      "t2_was_52w_high": false,
      "cached_for_trading_date": "2026-05-13"
    },
    "SOFI": {
      "high_52wk_t1": 32.209999084472656,
      "high_52wk_t2": 32.209999084472656,
      "high_52wk_t3": 32.209999084472656,
      "t1_close": 15.3100004196167,
      "t2_close": 15.899999618530273,
      "yesterday_was_52w_high": false,
      "t2_was_52w_high": false,
      "cached_for_trading_date": "2026-05-13"
    },
    "AUR": {
      "high_52wk_t1": 8.399999618530273,
      "high_52wk_t2": 7.929999828338623,
      "high_52wk_t3": 7.929999828338623,
      "t1_close": 8.399999618530273,
      "t2_close": 7.21999979019165,
      "yesterday_was_52w_high": true,
      "t2_was_52w_high": false,
      "cached_for_trading_date": "2026-05-13"
    },
    "MU": {
      "high_52wk_t1": 803.6300048828125,
      "high_52wk_t2": 795.3300170898438,
      "high_52wk_t3": 795.3300170898438,
      "t1_close": 803.6300048828125,
      "t2_close": 766.5800170898438,
      "yesterday_was_52w_high": true,
      "t2_was_52w_high": false,
      "cached_for_trading_date": "2026-05-13"
    },
    "PLTR": {
      "high_52wk_t1": 207.17999267578125,
      "high_52wk_t2": 207.17999267578125,
      "high_52wk_t3": 207.17999267578125,
      "t1_close": 130.0500030517578,
      "t2_close": 136,
      "yesterday_was_52w_high": false,
      "t2_was_52w_high": false,
      "cached_for_trading_date": "2026-05-13"
    },
    "NU": {
      "high_52wk_t1": 18.760000228881836,
      "high_52wk_t2": 18.760000228881836,
      "high_52wk_t3": 18.760000228881836,
      "t1_close": 12.819999694824219,
      "t2_close": 13.270000457763672,
      "yesterday_was_52w_high": false,
      "t2_was_52w_high": false,
      "cached_for_trading_date": "2026-05-13"
    },
    "GRAB": {
      "high_52wk_t1": 6.449999809265137,
      "high_52wk_t2": 6.449999809265137,
      "high_52wk_t3": 6.449999809265137,
      "t1_close": 3.630000114440918,
      "t2_close": 3.640000104904175,
      "yesterday_was_52w_high": false,
      "t2_was_52w_high": false,
      "cached_for_trading_date": "2026-05-13"
    },
    "IREN": {
      "high_52wk_t1": 76.41000366210938,
      "high_52wk_t2": 76.41000366210938,
      "high_52wk_t3": 76.41000366210938,
      "t1_close": 55.16999816894531,
      "t2_close": 56.560001373291016,
      "yesterday_was_52w_high": false,
      "t2_was_52w_high": false,
      "cached_for_trading_date": "2026-05-13"
    },
    "ACHR": {
      "high_52wk_t1": 13.640000343322754,
      "high_52wk_t2": 13.640000343322754,
      "high_52wk_t3": 13.640000343322754,
      "t1_close": 6.519999980926514,
      "t2_close": 6.389999866485596,
      "yesterday_was_52w_high": false,
      "t2_was_52w_high": false,
      "cached_for_trading_date": "2026-05-13"
    },
    "BBD": {
      "high_52wk_t1": 4.210000038146973,
      "high_52wk_t2": 4.210000038146973,
      "high_52wk_t3": 4.210000038146973,
      "t1_close": 3.509999990463257,
      "t2_close": 3.6500000953674316,
      "yesterday_was_52w_high": false,
      "t2_was_52w_high": false,
      "cached_for_trading_date": "2026-05-13"
    },
    "PATH": {
      "high_52wk_t1": 19.290000915527344,
      "high_52wk_t2": 19.290000915527344,
      "high_52wk_t3": 19.290000915527344,
      "t1_close": 9.470000267028809,
      "t2_close": 10.010000228881836,
      "yesterday_was_52w_high": false,
      "t2_was_52w_high": false,
      "cached_for_trading_date": "2026-05-13"
    },
    "POET": {
      "high_52wk_t1": 15.100000381469727,
      "high_52wk_t2": 15.100000381469727,
      "high_52wk_t3": 15.100000381469727,
      "t1_close": 14.369999885559082,
      "t2_close": 13.729999542236328,
      "yesterday_was_52w_high": false,
      "t2_was_52w_high": false,
      "cached_for_trading_date": "2026-05-13"
    },
    "AAPL": {
      "high_52wk_t1": 298.8699951171875,
      "high_52wk_t2": 294.79998779296875,
      "high_52wk_t3": 293.32000732421875,
      "t1_close": 298.8699951171875,
      "t2_close": 294.79998779296875,
      "yesterday_was_52w_high": true,
      "t2_was_52w_high": true,
      "cached_for_trading_date": "2026-05-13"
    },
    "BABA": {
      "high_52wk_t1": 189.33999633789062,
      "high_52wk_t2": 189.33999633789062,
      "high_52wk_t3": 189.33999633789062,
      "t1_close": 145.80999755859375,
      "t2_close": 134.77999877929688,
      "yesterday_was_52w_high": false,
      "t2_was_52w_high": false,
      "cached_for_trading_date": "2026-05-13"
    },
    "VALE": {
      "high_52wk_t1": 17.81999969482422,
      "high_52wk_t2": 17.81999969482422,
      "high_52wk_t3": 17.81999969482422,
      "t1_close": 16.84000015258789,
      "t2_close": 17.030000686645508,
      "yesterday_was_52w_high": false,
      "t2_was_52w_high": false,
      "cached_for_trading_date": "2026-05-13"
    },
    "NVTS": {
      "high_52wk_t1": 22.649999618530273,
      "high_52wk_t2": 22.649999618530273,
      "high_52wk_t3": 22.649999618530273,
      "t1_close": 21.170000076293945,
      "t2_close": 19.25,
      "yesterday_was_52w_high": false,
      "t2_was_52w_high": false,
      "cached_for_trading_date": "2026-05-13"
    },
    "BBAI": {
      "high_52wk_t1": 8.90999984741211,
      "high_52wk_t2": 8.90999984741211,
      "high_52wk_t3": 8.90999984741211,
      "t1_close": 4.210000038146973,
      "t2_close": 4.190000057220459,
      "yesterday_was_52w_high": false,
      "t2_was_52w_high": false,
      "cached_for_trading_date": "2026-05-13"
    },
    "SNAP": {
      "high_52wk_t1": 10.350000381469727,
      "high_52wk_t2": 10.350000381469727,
      "high_52wk_t3": 10.350000381469727,
      "t1_close": 5.610000133514404,
      "t2_close": 5.550000190734863,
      "yesterday_was_52w_high": false,
      "t2_was_52w_high": false,
      "cached_for_trading_date": "2026-05-13"
    },
    "NBIS": {
      "high_52wk_t1": 207.27000427246094,
      "high_52wk_t2": 195.08999633789062,
      "high_52wk_t3": 195.08999633789062,
      "t1_close": 207.27000427246094,
      "t2_close": 179.11000061035156,
      "yesterday_was_52w_high": true,
      "t2_was_52w_high": false,
      "cached_for_trading_date": "2026-05-13"
    },
    "AAL": {
      "high_52wk_t1": 16.260000228881836,
      "high_52wk_t2": 16.260000228881836,
      "high_52wk_t3": 16.260000228881836,
      "t1_close": 12.710000038146973,
      "t2_close": 12.6899995803833,
      "yesterday_was_52w_high": false,
      "t2_was_52w_high": false,
      "cached_for_trading_date": "2026-05-13"
    },
    "ITUB": {
      "high_52wk_t1": 9.569999694824219,
      "high_52wk_t2": 9.569999694824219,
      "high_52wk_t3": 9.569999694824219,
      "t1_close": 7.849999904632568,
      "t2_close": 8.100000381469727,
      "yesterday_was_52w_high": false,
      "t2_was_52w_high": false,
      "cached_for_trading_date": "2026-05-13"
    },
    "QUBT": {
      "high_52wk_t1": 24.6200008392334,
      "high_52wk_t2": 24.6200008392334,
      "high_52wk_t3": 24.6200008392334,
      "t1_close": 11.029999732971191,
      "t2_close": 11.779999732971191,
      "yesterday_was_52w_high": false,
      "t2_was_52w_high": false,
      "cached_for_trading_date": "2026-05-13"
    },
    "WOLF": {
      "high_52wk_t1": 62.599998474121094,
      "high_52wk_t2": 53.720001220703125,
      "high_52wk_t3": 50.310001373291016,
      "t1_close": 62.599998474121094,
      "t2_close": 53.720001220703125,
      "yesterday_was_52w_high": true,
      "t2_was_52w_high": true,
      "cached_for_trading_date": "2026-05-13"
    },
    "JD": {
      "high_52wk_t1": 37.25,
      "high_52wk_t2": 37.25,
      "high_52wk_t3": 37.25,
      "t1_close": 33.77000045776367,
      "t2_close": 31.489999771118164,
      "yesterday_was_52w_high": false,
      "t2_was_52w_high": false,
      "cached_for_trading_date": "2026-05-13"
    },
    "JOBY": {
      "high_52wk_t1": 20.389999389648438,
      "high_52wk_t2": 20.389999389648438,
      "high_52wk_t3": 20.389999389648438,
      "t1_close": 11.0600004196167,
      "t2_close": 10.489999771118164,
      "yesterday_was_52w_high": false,
      "t2_was_52w_high": false,
      "cached_for_trading_date": "2026-05-13"
    },
    "AMZN": {
      "high_52wk_t1": 274.989990234375,
      "high_52wk_t2": 274.989990234375,
      "high_52wk_t3": 274.989990234375,
      "t1_close": 270.1300048828125,
      "t2_close": 265.82000732421875,
      "yesterday_was_52w_high": false,
      "t2_was_52w_high": false,
      "cached_for_trading_date": "2026-05-13"
    },
    "MARA": {
      "high_52wk_t1": 22.84000015258789,
      "high_52wk_t2": 22.84000015258789,
      "high_52wk_t3": 22.84000015258789,
      "t1_close": 12.75,
      "t2_close": 12.720000267028809,
      "yesterday_was_52w_high": false,
      "t2_was_52w_high": false,
      "cached_for_trading_date": "2026-05-13"
    },
    "VG": {
      "high_52wk_t1": 19.010000228881836,
      "high_52wk_t2": 19.010000228881836,
      "high_52wk_t3": 19.010000228881836,
      "t1_close": 13,
      "t2_close": 13.270000457763672,
      "yesterday_was_52w_high": false,
      "t2_was_52w_high": false,
      "cached_for_trading_date": "2026-05-13"
    },
    "OPEN": {
      "high_52wk_t1": 10.520000457763672,
      "high_52wk_t2": 10.520000457763672,
      "high_52wk_t3": 10.520000457763672,
      "t1_close": 4.579999923706055,
      "t2_close": 4.710000038146973,
      "yesterday_was_52w_high": false,
      "t2_was_52w_high": false,
      "cached_for_trading_date": "2026-05-13"
    },
    "APLS": {
      "high_52wk_t1": 41.119998931884766,
      "high_52wk_t2": 41.119998931884766,
      "high_52wk_t3": 41.119998931884766,
      "t1_close": 41.029998779296875,
      "t2_close": 41.060001373291016,
      "yesterday_was_52w_high": false,
      "t2_was_52w_high": false,
      "cached_for_trading_date": "2026-05-13"
    },
    "RKT": {
      "high_52wk_t1": 23.440000534057617,
      "high_52wk_t2": 23.440000534057617,
      "high_52wk_t3": 23.440000534057617,
      "t1_close": 13.84000015258789,
      "t2_close": 14.800000190734863,
      "yesterday_was_52w_high": false,
      "t2_was_52w_high": false,
      "cached_for_trading_date": "2026-05-13"
    },
    "AMD": {
      "high_52wk_t1": 458.7900085449219,
      "high_52wk_t2": 458.7900085449219,
      "high_52wk_t3": 458.7900085449219,
      "t1_close": 445.5,
      "t2_close": 448.2900085449219,
      "yesterday_was_52w_high": false,
      "t2_was_52w_high": false,
      "cached_for_trading_date": "2026-05-13"
    },
    "CIFR": {
      "high_52wk_t1": 24.709999084472656,
      "high_52wk_t2": 24.709999084472656,
      "high_52wk_t3": 24.709999084472656,
      "t1_close": 21.239999771118164,
      "t2_close": 20.059999465942383,
      "yesterday_was_52w_high": false,
      "t2_was_52w_high": false,
      "cached_for_trading_date": "2026-05-13"
    },
    "LCID": {
      "high_52wk_t1": 31.299999237060547,
      "high_52wk_t2": 31.299999237060547,
      "high_52wk_t3": 31.299999237060547,
      "t1_close": 6.389999866485596,
      "t2_close": 6.010000228881836,
      "yesterday_was_52w_high": false,
      "t2_was_52w_high": false,
      "cached_for_trading_date": "2026-05-13"
    },
    "T": {
      "high_52wk_t1": 29.6200008392334,
      "high_52wk_t2": 29.6200008392334,
      "high_52wk_t3": 29.6200008392334,
      "t1_close": 24.739999771118164,
      "t2_close": 25.229999542236328,
      "yesterday_was_52w_high": false,
      "t2_was_52w_high": false,
      "cached_for_trading_date": "2026-05-13"
    },
    "CMCSA": {
      "high_52wk_t1": 34.048736572265625,
      "high_52wk_t2": 34.048736572265625,
      "high_52wk_t3": 34.048736572265625,
      "t1_close": 24.940000534057617,
      "t2_close": 24.899999618530273,
      "yesterday_was_52w_high": false,
      "t2_was_52w_high": false,
      "cached_for_trading_date": "2026-05-13"
    },
    "ABEV": {
      "high_52wk_t1": 3.430000066757202,
      "high_52wk_t2": 3.430000066757202,
      "high_52wk_t3": 3.430000066757202,
      "t1_close": 3.1500000953674316,
      "t2_close": 3.259999990463257,
      "yesterday_was_52w_high": false,
      "t2_was_52w_high": false,
      "cached_for_trading_date": "2026-05-13"
    },
    "TSM": {
      "high_52wk_t1": 419.5,
      "high_52wk_t2": 419.5,
      "high_52wk_t3": 419.5,
      "t1_close": 399.79998779296875,
      "t2_close": 397.2799987792969,
      "yesterday_was_52w_high": false,
      "t2_was_52w_high": false,
      "cached_for_trading_date": "2026-05-13"
    },
    "RDW": {
      "high_52wk_t1": 20.56999969482422,
      "high_52wk_t2": 20.56999969482422,
      "high_52wk_t3": 20.56999969482422,
      "t1_close": 11.460000038146973,
      "t2_close": 11.5600004196167,
      "yesterday_was_52w_high": false,
      "t2_was_52w_high": false,
      "cached_for_trading_date": "2026-05-13"
    },
    "SNAL": {
      "high_52wk_t1": 1.7000000476837158,
      "high_52wk_t2": 1.7000000476837158,
      "high_52wk_t3": 1.7000000476837158,
      "t1_close": 0.5019999742507935,
      "t2_close": 0.503000020980835,
      "yesterday_was_52w_high": false,
      "t2_was_52w_high": false,
      "cached_for_trading_date": "2026-05-13"
    },
    "MOBX": {
      "high_52wk_t1": 12.100000381469727,
      "high_52wk_t2": 12.100000381469727,
      "high_52wk_t3": 12.100000381469727,
      "t1_close": 1.7400000095367432,
      "t2_close": 1.9299999475479126,
      "yesterday_was_52w_high": false,
      "t2_was_52w_high": false,
      "cached_for_trading_date": "2026-05-13"
    },
    "BA": {
      "high_52wk_t1": 252.14999389648438,
      "high_52wk_t2": 252.14999389648438,
      "high_52wk_t3": 252.14999389648438,
      "t1_close": 240.60000610351562,
      "t2_close": 236.8699951171875,
      "yesterday_was_52w_high": false,
      "t2_was_52w_high": false,
      "cached_for_trading_date": "2026-05-13"
    },
    "KLAR": {
      "high_52wk_t1": 45.47999954223633,
      "high_52wk_t2": 45.47999954223633,
      "high_52wk_t3": 45.47999954223633,
      "t1_close": 13.6899995803833,
      "t2_close": 14.130000114440918,
      "yesterday_was_52w_high": false,
      "t2_was_52w_high": false,
      "cached_for_trading_date": "2026-05-13"
    },
    "TTWO": {
      "high_52wk_t1": 262.2900085449219,
      "high_52wk_t2": 262.2900085449219,
      "high_52wk_t3": 262.2900085449219,
      "t1_close": 226.99000549316406,
      "t2_close": 225.99000549316406,
      "yesterday_was_52w_high": false,
      "t2_was_52w_high": false,
      "cached_for_trading_date": "2026-05-13"
    },
    "ALP": {
      "high_52wk_t1": 10.90999984741211,
      "high_52wk_t2": 10.90999984741211,
      "high_52wk_t3": 10.90999984741211,
      "t1_close": 0.2680000066757202,
      "t2_close": 0.2750000059604645,
      "yesterday_was_52w_high": false,
      "t2_was_52w_high": false,
      "cached_for_trading_date": "2026-05-13"
    },
    "STUB": {
      "high_52wk_t1": 22,
      "high_52wk_t2": 22,
      "high_52wk_t3": 22,
      "t1_close": 7.519999980926514,
      "t2_close": 7.320000171661377,
      "yesterday_was_52w_high": false,
      "t2_was_52w_high": false,
      "cached_for_trading_date": "2026-05-13"
    },
    "MFC.TO": {
      "high_52wk_t1": 54.81999969482422,
      "high_52wk_t2": 54.81999969482422,
      "high_52wk_t3": 54.720001220703125,
      "t1_close": 54.619998931884766,
      "t2_close": 54.81999969482422,
      "yesterday_was_52w_high": false,
      "t2_was_52w_high": true,
      "cached_for_trading_date": "2026-05-13"
    },
    "YOOV": {
      "high_52wk_t1": 28.18000030517578,
      "high_52wk_t2": 28.18000030517578,
      "high_52wk_t3": 28.18000030517578,
      "t1_close": 0.6930000185966492,
      "t2_close": 1.0199999809265137,
      "yesterday_was_52w_high": false,
      "t2_was_52w_high": false,
      "cached_for_trading_date": "2026-05-13"
    },
    "RGNX": {
      "high_52wk_t1": 15.979999542236328,
      "high_52wk_t2": 15.979999542236328,
      "high_52wk_t3": 15.979999542236328,
      "t1_close": 10.039999961853027,
      "t2_close": 10.239999771118164,
      "yesterday_was_52w_high": false,
      "t2_was_52w_high": false,
      "cached_for_trading_date": "2026-05-13"
    },
    "APLD": {
      "high_52wk_t1": 45.47999954223633,
      "high_52wk_t2": 44.59000015258789,
      "high_52wk_t3": 44.59000015258789,
      "t1_close": 45.47999954223633,
      "t2_close": 43.93000030517578,
      "yesterday_was_52w_high": true,
      "t2_was_52w_high": false,
      "cached_for_trading_date": "2026-05-13"
    },
    "PCT": {
      "high_52wk_t1": 16.920000076293945,
      "high_52wk_t2": 16.920000076293945,
      "high_52wk_t3": 16.920000076293945,
      "t1_close": 10.199999809265137,
      "t2_close": 9.760000228881836,
      "yesterday_was_52w_high": false,
      "t2_was_52w_high": false,
      "cached_for_trading_date": "2026-05-13"
    },
    "KEEL": {
      "high_52wk_t1": 6.46999979019165,
      "high_52wk_t2": 6.46999979019165,
      "high_52wk_t3": 6.46999979019165,
      "t1_close": 4.150000095367432,
      "t2_close": 4.070000171661377,
      "yesterday_was_52w_high": false,
      "t2_was_52w_high": false,
      "cached_for_trading_date": "2026-05-13"
    },
    "SMCI": {
      "high_52wk_t1": 60.709999084472656,
      "high_52wk_t2": 60.709999084472656,
      "high_52wk_t3": 60.709999084472656,
      "t1_close": 32,
      "t2_close": 32.790000915527344,
      "yesterday_was_52w_high": false,
      "t2_was_52w_high": false,
      "cached_for_trading_date": "2026-05-13"
    },
    "LUMN": {
      "high_52wk_t1": 11.829999923706055,
      "high_52wk_t2": 11.829999923706055,
      "high_52wk_t3": 11.829999923706055,
      "t1_close": 9.399999618530273,
      "t2_close": 8.670000076293945,
      "yesterday_was_52w_high": false,
      "t2_was_52w_high": false,
      "cached_for_trading_date": "2026-05-13"
    },
    "BMNR": {
      "high_52wk_t1": 135,
      "high_52wk_t2": 135,
      "high_52wk_t3": 135,
      "t1_close": 21.18000030517578,
      "t2_close": 21.670000076293945,
      "yesterday_was_52w_high": false,
      "t2_was_52w_high": false,
      "cached_for_trading_date": "2026-05-13"
    },
    "RGTI": {
      "high_52wk_t1": 56.34000015258789,
      "high_52wk_t2": 56.34000015258789,
      "high_52wk_t3": 56.34000015258789,
      "t1_close": 18.415000915527344,
      "t2_close": 19.06999969482422,
      "yesterday_was_52w_high": false,
      "t2_was_52w_high": false,
      "cached_for_trading_date": "2026-05-13"
    },
    "FIG": {
      "high_52wk_t1": 122,
      "high_52wk_t2": 122,
      "high_52wk_t3": 122,
      "t1_close": 18.940000534057617,
      "t2_close": 19.329999923706055,
      "yesterday_was_52w_high": false,
      "t2_was_52w_high": false,
      "cached_for_trading_date": "2026-05-13"
    },
    "CRWV": {
      "high_52wk_t1": 183.5800018310547,
      "high_52wk_t2": 183.5800018310547,
      "high_52wk_t3": 183.5800018310547,
      "t1_close": 111.30999755859375,
      "t2_close": 107.75,
      "yesterday_was_52w_high": false,
      "t2_was_52w_high": false,
      "cached_for_trading_date": "2026-05-13"
    },
    "NOW": {
      "high_52wk_t1": 208.93800354003906,
      "high_52wk_t2": 208.93800354003906,
      "high_52wk_t3": 208.93800354003906,
      "t1_close": 87.05000305175781,
      "t2_close": 89,
      "yesterday_was_52w_high": false,
      "t2_was_52w_high": false,
      "cached_for_trading_date": "2026-05-13"
    },
    "QBTS": {
      "high_52wk_t1": 44.779998779296875,
      "high_52wk_t2": 44.779998779296875,
      "high_52wk_t3": 44.779998779296875,
      "t1_close": 21.440000534057617,
      "t2_close": 22.350000381469727,
      "yesterday_was_52w_high": false,
      "t2_was_52w_high": false,
      "cached_for_trading_date": "2026-05-13"
    },
    "ASTS": {
      "high_52wk_t1": 122.08999633789062,
      "high_52wk_t2": 122.08999633789062,
      "high_52wk_t3": 122.08999633789062,
      "t1_close": 74.80999755859375,
      "t2_close": 72.95999908447266,
      "yesterday_was_52w_high": false,
      "t2_was_52w_high": false,
      "cached_for_trading_date": "2026-05-13"
    },
    "COIN": {
      "high_52wk_t1": 419.7799987792969,
      "high_52wk_t2": 419.7799987792969,
      "high_52wk_t3": 419.7799987792969,
      "t1_close": 201.8000030517578,
      "t2_close": 207.63999938964844,
      "yesterday_was_52w_high": false,
      "t2_was_52w_high": false,
      "cached_for_trading_date": "2026-05-13"
    },
    "MSTR": {
      "high_52wk_t1": 455.8999938964844,
      "high_52wk_t2": 455.8999938964844,
      "high_52wk_t3": 455.8999938964844,
      "t1_close": 178.02999877929688,
      "t2_close": 184.4199981689453,
      "yesterday_was_52w_high": false,
      "t2_was_52w_high": false,
      "cached_for_trading_date": "2026-05-13"
    },
    "LESL": {
      "high_52wk_t1": 18.260000228881836,
      "high_52wk_t2": 18.260000228881836,
      "high_52wk_t3": 18.260000228881836,
      "t1_close": 1.4299999475479126,
      "t2_close": 1.5099999904632568,
      "yesterday_was_52w_high": false,
      "t2_was_52w_high": false,
      "cached_for_trading_date": "2026-05-13"
    },
    "CREG": {
      "high_52wk_t1": 7.800000190734863,
      "high_52wk_t2": 7.800000190734863,
      "high_52wk_t3": 7.800000190734863,
      "t1_close": 0.20000000298023224,
      "t2_close": 0.25,
      "yesterday_was_52w_high": false,
      "t2_was_52w_high": false,
      "cached_for_trading_date": "2026-05-13"
    },
    "DGXX": {
      "high_52wk_t1": 8.460000038146973,
      "high_52wk_t2": 8.390000343322754,
      "high_52wk_t3": 7.429999828338623,
      "t1_close": 8.460000038146973,
      "t2_close": 8.390000343322754,
      "yesterday_was_52w_high": true,
      "t2_was_52w_high": true,
      "cached_for_trading_date": "2026-05-13"
    },
    "BAC": {
      "high_52wk_t1": 57.25,
      "high_52wk_t2": 57.25,
      "high_52wk_t3": 57.25,
      "t1_close": 49.84000015258789,
      "t2_close": 50.779998779296875,
      "yesterday_was_52w_high": false,
      "t2_was_52w_high": false,
      "cached_for_trading_date": "2026-05-13"
    },
    "HOOD": {
      "high_52wk_t1": 152.4600067138672,
      "high_52wk_t2": 152.4600067138672,
      "high_52wk_t3": 152.4600067138672,
      "t1_close": 76.75,
      "t2_close": 78.2699966430664,
      "yesterday_was_52w_high": false,
      "t2_was_52w_high": false,
      "cached_for_trading_date": "2026-05-13"
    },
    "SMR": {
      "high_52wk_t1": 53.43000030517578,
      "high_52wk_t2": 53.43000030517578,
      "high_52wk_t3": 53.43000030517578,
      "t1_close": 11.960000038146973,
      "t2_close": 12,
      "yesterday_was_52w_high": false,
      "t2_was_52w_high": false,
      "cached_for_trading_date": "2026-05-13"
    }
  }
}