{
  "source_id": "trending",
  "source_label": "Trending",
  "source_url": "https://finance.yahoo.com/markets/stocks/trending/",
  "last_updated_iso": "2026-05-19T16:14:51.191Z",
  "fetched_count": 25,
  "rows": [
    {
      "rank": 1,
      "ticker": "WNW",
      "name": "Meiwu Technology Company Limite",
      "current_price": 5.85,
      "market_cap_bn": 0.01,
      "outside_rth_price": null,
      "outside_rth_side": null,
      "outside_rth_time_iso": null,
      "yahoo_url": "https://finance.yahoo.com/quote/WNW"
    },
    {
      "rank": 2,
      "ticker": "HD",
      "name": "Home Depot, Inc. (The)",
      "current_price": 301.86,
      "market_cap_bn": 300.66,
      "outside_rth_price": null,
      "outside_rth_side": null,
      "outside_rth_time_iso": null,
      "yahoo_url": "https://finance.yahoo.com/quote/HD"
    },
    {
      "rank": 3,
      "ticker": "AMST",
      "name": "Amesite Inc.",
      "current_price": 1.95,
      "market_cap_bn": 0.01,
      "outside_rth_price": null,
      "outside_rth_side": null,
      "outside_rth_time_iso": null,
      "yahoo_url": "https://finance.yahoo.com/quote/AMST"
    },
    {
      "rank": 4,
      "ticker": "RUBI",
      "name": "Rubico Inc.",
      "current_price": 1.6593,
      "market_cap_bn": 0,
      "outside_rth_price": null,
      "outside_rth_side": null,
      "outside_rth_time_iso": null,
      "yahoo_url": "https://finance.yahoo.com/quote/RUBI"
    },
    {
      "rank": 5,
      "ticker": "COST",
      "name": "Costco Wholesale Corporation",
      "current_price": 1094.15,
      "market_cap_bn": 485.42,
      "outside_rth_price": null,
      "outside_rth_side": null,
      "outside_rth_time_iso": null,
      "yahoo_url": "https://finance.yahoo.com/quote/COST"
    },
    {
      "rank": 6,
      "ticker": "INM",
      "name": "InMed Pharmaceuticals Inc.",
      "current_price": 1.4899,
      "market_cap_bn": 0,
      "outside_rth_price": null,
      "outside_rth_side": null,
      "outside_rth_time_iso": null,
      "yahoo_url": "https://finance.yahoo.com/quote/INM"
    },
    {
      "rank": 7,
      "ticker": "CSU.TO",
      "name": "CONSTELLATION SOFTWARE INC.",
      "current_price": 2849.89,
      "market_cap_bn": 60.39,
      "outside_rth_price": null,
      "outside_rth_side": null,
      "outside_rth_time_iso": null,
      "yahoo_url": "https://finance.yahoo.com/quote/CSU.TO"
    },
    {
      "rank": 8,
      "ticker": "AGYS",
      "name": "Agilysys, Inc.",
      "current_price": 79.445,
      "market_cap_bn": 2.23,
      "outside_rth_price": null,
      "outside_rth_side": null,
      "outside_rth_time_iso": null,
      "yahoo_url": "https://finance.yahoo.com/quote/AGYS"
    },
    {
      "rank": 9,
      "ticker": "CODX",
      "name": "Co-Diagnostics, Inc.",
      "current_price": 2.1211,
      "market_cap_bn": 0.01,
      "outside_rth_price": null,
      "outside_rth_side": null,
      "outside_rth_time_iso": null,
      "yahoo_url": "https://finance.yahoo.com/quote/CODX"
    },
    {
      "rank": 10,
      "ticker": "AMD",
      "name": "Advanced Micro Devices, Inc.",
      "current_price": 409.62,
      "market_cap_bn": 667.93,
      "outside_rth_price": null,
      "outside_rth_side": null,
      "outside_rth_time_iso": null,
      "yahoo_url": "https://finance.yahoo.com/quote/AMD"
    },
    {
      "rank": 11,
      "ticker": "SNOW",
      "name": "Snowflake Inc.",
      "current_price": 167.62,
      "market_cap_bn": 57.95,
      "outside_rth_price": null,
      "outside_rth_side": null,
      "outside_rth_time_iso": null,
      "yahoo_url": "https://finance.yahoo.com/quote/SNOW"
    },
    {
      "rank": 12,
      "ticker": "GIPR",
      "name": "Generation Income Properties In",
      "current_price": 0.4536,
      "market_cap_bn": 0,
      "outside_rth_price": null,
      "outside_rth_side": null,
      "outside_rth_time_iso": null,
      "yahoo_url": "https://finance.yahoo.com/quote/GIPR"
    },
    {
      "rank": 13,
      "ticker": "RLAY",
      "name": "Relay Therapeutics, Inc.",
      "current_price": 12.965,
      "market_cap_bn": 2.48,
      "outside_rth_price": null,
      "outside_rth_side": null,
      "outside_rth_time_iso": null,
      "yahoo_url": "https://finance.yahoo.com/quote/RLAY"
    },
    {
      "rank": 14,
      "ticker": "BKKT",
      "name": "Bakkt, Inc.",
      "current_price": 9.8507,
      "market_cap_bn": 0.44,
      "outside_rth_price": null,
      "outside_rth_side": null,
      "outside_rth_time_iso": null,
      "yahoo_url": "https://finance.yahoo.com/quote/BKKT"
    },
    {
      "rank": 15,
      "ticker": "MTVA",
      "name": "MetaVia Inc.",
      "current_price": 1.7,
      "market_cap_bn": 0.01,
      "outside_rth_price": null,
      "outside_rth_side": null,
      "outside_rth_time_iso": null,
      "yahoo_url": "https://finance.yahoo.com/quote/MTVA"
    },
    {
      "rank": 16,
      "ticker": "HUT.TO",
      "name": "HUT 8 CORP",
      "current_price": 124.91,
      "market_cap_bn": 14.06,
      "outside_rth_price": null,
      "outside_rth_side": null,
      "outside_rth_time_iso": null,
      "yahoo_url": "https://finance.yahoo.com/quote/HUT.TO"
    },
    {
      "rank": 17,
      "ticker": "ENB.TO",
      "name": "ENBRIDGE INC",
      "current_price": 78.025,
      "market_cap_bn": 170.38,
      "outside_rth_price": null,
      "outside_rth_side": null,
      "outside_rth_time_iso": null,
      "yahoo_url": "https://finance.yahoo.com/quote/ENB.TO"
    },
    {
      "rank": 18,
      "ticker": "CLS.TO",
      "name": "CELESTICA INC",
      "current_price": 462.06,
      "market_cap_bn": 53.12,
      "outside_rth_price": null,
      "outside_rth_side": null,
      "outside_rth_time_iso": null,
      "yahoo_url": "https://finance.yahoo.com/quote/CLS.TO"
    },
    {
      "rank": 19,
      "ticker": "SFM",
      "name": "Sprouts Farmers Market, Inc.",
      "current_price": 94.15,
      "market_cap_bn": 8.85,
      "outside_rth_price": null,
      "outside_rth_side": null,
      "outside_rth_time_iso": null,
      "yahoo_url": "https://finance.yahoo.com/quote/SFM"
    },
    {
      "rank": 20,
      "ticker": "SHOP.TO",
      "name": "SHOPIFY INC",
      "current_price": 139.07,
      "market_cap_bn": 180.46,
      "outside_rth_price": null,
      "outside_rth_side": null,
      "outside_rth_time_iso": null,
      "yahoo_url": "https://finance.yahoo.com/quote/SHOP.TO"
    },
    {
      "rank": 21,
      "ticker": "CMBT",
      "name": "CMB.TECH NV",
      "current_price": 16.89,
      "market_cap_bn": 4.9,
      "outside_rth_price": null,
      "outside_rth_side": null,
      "outside_rth_time_iso": null,
      "yahoo_url": "https://finance.yahoo.com/quote/CMBT"
    },
    {
      "rank": 22,
      "ticker": "DIV.TO",
      "name": "DIVERSIFIED ROYALTY CORP",
      "current_price": 4.69,
      "market_cap_bn": 0.8,
      "outside_rth_price": null,
      "outside_rth_side": null,
      "outside_rth_time_iso": null,
      "yahoo_url": "https://finance.yahoo.com/quote/DIV.TO"
    },
    {
      "rank": 23,
      "ticker": "HIVE.TO",
      "name": "HIVE DIGITAL TECHNOLOGIES LTD",
      "current_price": 4.345,
      "market_cap_bn": 1.1,
      "outside_rth_price": null,
      "outside_rth_side": null,
      "outside_rth_time_iso": null,
      "yahoo_url": "https://finance.yahoo.com/quote/HIVE.TO"
    },
    {
      "rank": 24,
      "ticker": "HSAI",
      "name": "Hesai Group",
      "current_price": 19.615,
      "market_cap_bn": 3.08,
      "outside_rth_price": null,
      "outside_rth_side": null,
      "outside_rth_time_iso": null,
      "yahoo_url": "https://finance.yahoo.com/quote/HSAI"
    },
    {
      "rank": 25,
      "ticker": "CRDF",
      "name": "Cardiff Oncology, Inc.",
      "current_price": 1.86,
      "market_cap_bn": 0.13,
      "outside_rth_price": null,
      "outside_rth_side": null,
      "outside_rth_time_iso": null,
      "yahoo_url": "https://finance.yahoo.com/quote/CRDF"
    }
  ]
}